lykeio/__init__.py
lykeio/base.py
lykeio/core.py
lykeio/courses/card_games/__init__.py
lykeio/courses/card_games/blackjack.py
lykeio/courses/word_games/mmlunaire.py
lykeio-0.1.0.dist-info/LICENSES/GPLv3.txt
lykeio-0.1.0.dist-info/LICENSES/TPLv1.txt
lykeio-0.1.0.dist-info/METADATA
lykeio-0.1.0.dist-info/WHEEL
lykeio-0.1.0.dist-info/RECORD
