Metadata-Version: 2.3
Name: lykeio
Version: 0.1.0
Summary: 
Author: Vasilis Valatsos
Author-email: aethrvmn@apotheke.earth
Requires-Python: >=3.13
Classifier: Programming Language :: Python :: 3
Classifier: Programming Language :: Python :: 3.13
Requires-Dist: mcp (>=1.9.4,<2.0.0)
